urbandic/__init__.py
urbandic/urbandic.py
urbandic-1.0.0.dist-info/METADATA
urbandic-1.0.0.dist-info/WHEEL
urbandic-1.0.0.dist-info/top_level.txt
urbandic-1.0.0.dist-info/RECORD
