Metadata-Version: 2.1
Name: urbandic
Version: 1.0.0
Summary: Urban Dictionary API client
Home-page: https://github.com/thexxiv/urbandictionary-py
Author: XXIV
License: UNKNOWN
Project-URL: Bug Tracker, https://github.com/thexxiv/urbandictionary-py/issues
Platform: UNKNOWN
Classifier: Programming Language :: Python :: 3
Classifier: License :: OSI Approved :: MIT License
Classifier: Operating System :: OS Independent
Requires-Python: >=3.6
